<?xml version="1.0" encoding="utf-8" ?>
<dwsync>
<file name="avatar_female.png" server="138.197.118.171//var/www/html/" local="131357186246574690" remote="131357186750000000" Dst="1" />
<file name="avatar_male.png" server="138.197.118.171//var/www/html/" local="131357186419771672" remote="131357186760000000" Dst="1" />
<file name="receita.png" server="138.197.118.171//var/www/html/" local="131375085724746508" remote="131375087340000000" Dst="1" />
<file name="receita_white.png" server="138.197.118.171//var/www/html/" local="131375106350775470" remote="131375106490000000" Dst="1" />
<file name="logo_pasang_branca_horizontal.png" server="127.0.0.1//var/www/cms.popepper.com.br/" local="131390096685777312" remote="131390098800000000" Dst="1" />
<file name="cart.png" server="127.0.0.1//var/www/cms.popepper.com.br/" local="131588795863005518" remote="131588795400000000" Dst="2" />
<file name="black_1_1.jpg" server="127.0.0.1//var/www/cms.popepper.com.br/" local="131595502847547918" remote="131595502800000000" Dst="2" />
<file name="logo_pasang_colorida_horizontal.jpg" server="127.0.0.1//var/www/cms.popepper.com.br/" local="131600643669127652" remote="131600643600000000" Dst="2" />
<file name="avatar_undefined.png" server="127.0.0.1//var/www/cms.popepper.com.br/" local="131604333498901525" remote="131604333600000000" Dst="2" />
<file name="preview-android.svg" server="127.0.0.1//var/www/cms.popepper.com.br/" local="131619727924066701" remote="131619734400000000" Dst="2" />
<file name="preview-iphone.svg" server="127.0.0.1//var/www/cms.popepper.com.br/" local="131619727850239467" remote="131619734400000000" Dst="2" />
<file name="stopwatch.gif" server="127.0.0.1//data/www/html/cms.popepper.com.br/" local="131879829048468510" remote="131879829000000000" Dst="2" />
<file name="logo_yeapps.png" server="127.0.0.1//data/www/html/cms.yeapps.com.br/" local="131933373800000000" remote="132272106000000000" Dst="0" />
<file name="human_body.png" server="127.0.0.1//var/www/html/" local="132488885390570232" remote="132488885400000000" Dst="0" />
<file name="fundo_amarelo.png" server="127.0.0.1//var/www/html/" local="132488961062990718" remote="132488961000000000" Dst="0" />
<file name="favicon_colorido.png" server="127.0.0.1//var/www/html/" local="132596858473643866" remote="132596858400000000" Dst="0" />
<file name="any.png" server="127.0.0.1//var/www/html/" local="132428279770000000" remote="132604829400000000" Dst="0" />
<file name="apartment.png" server="127.0.0.1//var/www/html/" local="130457364964127620" remote="132604829400000000" Dst="0" />
<file name="avatar_female.png" server="127.0.0.1//var/www/html/" local="132398937810000000" remote="132604829400000000" Dst="0" />
<file name="avatar_male.png" server="127.0.0.1//var/www/html/" local="132398937810000000" remote="132604829400000000" Dst="0" />
<file name="avatar_undefined.png" server="127.0.0.1//var/www/html/" local="132398937810000000" remote="132604829400000000" Dst="0" />
<file name="black_1_1.jpg" server="127.0.0.1//var/www/html/" local="132398937810000000" remote="132604829400000000" Dst="0" />
<file name="cart.png" server="127.0.0.1//var/www/html/" local="132398937810000000" remote="132604829400000000" Dst="0" />
<file name="condominium.png" server="127.0.0.1//var/www/html/" local="130457364931625761" remote="132604829400000000" Dst="0" />
<file name="construction-site.png" server="127.0.0.1//var/www/html/" local="130457364864251907" remote="132604829400000000" Dst="0" />
<file name="cottage.png" server="127.0.0.1//var/www/html/" local="130457364827409800" remote="132604829400000000" Dst="0" />
<file name="empty.png" server="127.0.0.1//var/www/html/" local="130457355190758615" remote="132604829400000000" Dst="0" />
<file name="garage.png" server="127.0.0.1//var/www/html/" local="130457364787337508" remote="132604829400000000" Dst="0" />
<file name="houseboat.png" server="127.0.0.1//var/www/html/" local="130457364753235557" remote="132604829400000000" Dst="0" />
<file name="icon_push_sms.png" server="127.0.0.1//var/www/html/" local="132422216470000000" remote="132604829400000000" Dst="0" />
<file name="icon_push_whatsapp.png" server="127.0.0.1//var/www/html/" local="132422216500000000" remote="132604829400000000" Dst="0" />
<file name="industrial-site.png" server="127.0.0.1//var/www/html/" local="130457364717613520" remote="132604829400000000" Dst="0" />
<file name="land.png" server="127.0.0.1//var/www/html/" local="130457364680251383" remote="132604829400000000" Dst="0" />
<file name="logo_pasang_branca_horizontal.png" server="127.0.0.1//var/www/html/" local="132398937810000000" remote="132604829400000000" Dst="0" />
<file name="logo_pasang_colorida_horizontal.jpg" server="127.0.0.1//var/www/html/" local="132398937810000000" remote="132604829400000000" Dst="0" />
<file name="logo_yeapps.png" server="127.0.0.1//var/www/html/" local="132398937810000000" remote="132604829400000000" Dst="0" />
<file name="preview-android.svg" server="127.0.0.1//var/www/html/" local="132398937810000000" remote="132604829400000000" Dst="0" />
<file name="preview-iphone.svg" server="127.0.0.1//var/www/html/" local="132398937810000000" remote="132604829400000000" Dst="0" />
<file name="receita.png" server="127.0.0.1//var/www/html/" local="132398937810000000" remote="132604829400000000" Dst="0" />
<file name="receita_white.png" server="127.0.0.1//var/www/html/" local="132398937810000000" remote="132604829400000000" Dst="0" />
<file name="single-family.png" server="127.0.0.1//var/www/html/" local="130457364618787867" remote="132604829400000000" Dst="0" />
<file name="villa.png" server="127.0.0.1//var/www/html/" local="130457364460568818" remote="132604829400000000" Dst="0" />
<file name="vineyard.png" server="127.0.0.1//var/www/html/" local="130457361951485306" remote="132604829400000000" Dst="0" />
<file name="warehouse.png" server="127.0.0.1//var/www/html/" local="130457361880741260" remote="132604829400000000" Dst="0" />
<file name="stopwatch.gif" server="127.0.0.1//var/www/html/" local="132398937810000000" remote="132604829400000000" Dst="0" />
<file name="close-btn.png" server="127.0.0.1//var/www/html/" local="130416054861892742" remote="132604831200000000" Dst="0" />
<file name="cluster.png" server="127.0.0.1//var/www/html/" local="130470533158068152" remote="132604831200000000" Dst="0" />
<file name="marker.png" server="127.0.0.1//var/www/html/" local="130457310827591187" remote="132604831200000000" Dst="0" />
<file name="iphone-slider.png" server="127.0.0.1//var/www/html/" local="132709154769214704" remote="132709155600000000" Dst="0" />
</dwsync>